{
    "title": "フクキタル的オマジナイ",
    "no_wrap": false,
    "text_block_list": [
        {
            "name": "",
            "text": "出かけた後、マチカネフクキタルとともに\r\n学園へ帰ってくると――"
        },
        {
            "name": "",
            "text": "何かに躓いて転んでしまった……。"
        },
        {
            "name": "マチカネフクキタル",
            "text": "おおっ！？\r\n大丈夫ですか、トレーナーさん！"
        },
        {
            "name": "マチカネフクキタル",
            "text": "って、なあああああっ！\r\nく、くく靴ひも切れちゃってますよぅ！？"
        },
        {
            "name": "マチカネフクキタル",
            "text": "下駄の鼻緒が切れるなど！\r\n大殺界のバーゲンセール待ったなし！"
        },
        {
            "name": "マチカネフクキタル",
            "text": "……あれ！？\r\nなんかこんなこと前にもありませんでした！？"
        },
        {
            "name": "マチカネフクキタル",
            "text": "いやそんなことより、これは一大事です！\r\n今すぐトレーナーさんの厄除けをせねば！"
        },
        {
            "name": "マチカネフクキタル",
            "text": "よし、最近インターネットで仕入れた、\r\n運気アップのオマジナイをしましょう！"
        },
        {
            "name": "マチカネフクキタル",
            "text": "手をつないで運気アップのオマジナイ、\r\n『手つなぎ』です！",
            "choice_data_list": [
                "え！？"
            ]
        },
        {
            "name": "マチカネフクキタル",
            "text": "さあさあ、私の手をとってください！",
            "choice_data_list": [
                "いや、でも……"
            ]
        },
        {
            "name": "マチカネフクキタル",
            "text": "ためらっている時間はありませんよ！！\r\n大殺界がやってきてしまいます！！"
        },
        {
            "name": "マチカネフクキタル",
            "text": "さあ、早く！",
            "choice_data_list": [
                "手を取る",
                "ハイタッチでごまかす",
                "丁重に断る"
            ]
        },
        {
            "name": "マチカネフクキタル",
            "text": "さていざ、運気アップです！\r\nとぉーっ！！"
        },
        {
            "name": "マチカネフクキタル",
            "text": "ほら、ぽかぽかな幸運パワーが、\r\n流れ込んできたでしょう～？"
        },
        {
            "name": "マチカネフクキタル",
            "text": "ほわわ……なんだか、ほかの方とするよりも\r\nぽかぽかが強いですねぇ。"
        },
        {
            "name": "マチカネフクキタル",
            "text": "もしや、トレーナーさんは、\r\n幸運パワーに満ち満ちた方なのでは！？"
        },
        {
            "name": "マチカネフクキタル",
            "text": "ふっふっふ、\r\nいいことに気づいてしまいました～！"
        },
        {
            "name": "",
            "text": "その後しばらく、運気の悪い日は\r\n『手つなぎ』をしようとしてくる\nマチカネフクキタルだった。"
        },
        {
            "name": "マチカネフクキタル",
            "text": "へ？　い、いえーい？"
        },
        {
            "name": "マチカネフクキタル",
            "text": "はっ、なんだかとっても\r\n楽しい気持ちになりました！"
        },
        {
            "name": "マチカネフクキタル",
            "text": "ハイタッチにはこんな秘められた力が！？\r\nよもや『手つなぎ』にも勝るのでは……！？"
        },
        {
            "name": "マチカネフクキタル",
            "text": "よし、いっぱいしましょう！\r\nハイタッチ！　いえーい！"
        },
        {
            "name": "マチカネフクキタル",
            "text": "あはははっ！　楽しいですね～！\r\nいえい、いえーいっ！"
        },
        {
            "name": "",
            "text": "その後数十分、正門でハイタッチをし続け、\r\n不思議と、楽しい気持ちで帰路についた。"
        },
        {
            "name": "マチカネフクキタル",
            "text": "ええっ！？　本当にいいんですか！？"
        },
        {
            "name": "マチカネフクキタル",
            "text": "はっ、優しいトレーナーさんのことです……\r\nよもや私の身を案じて！？"
        },
        {
            "name": "マチカネフクキタル",
            "text": "私に大殺界が流れ込んでくるのではないかと、\r\nそんな事態を危惧しているのでは……！？"
        },
        {
            "name": "マチカネフクキタル",
            "text": "そんなに気を使ってもらわなくとも！\r\nトレーナーとウマ娘は運命共同体ですから！"
        },
        {
            "name": "マチカネフクキタル",
            "text": "ですが、トレーナーさんの\r\n優しさはわかりました。\nここは別のオマジナイにしておきますっ！"
        },
        {
            "name": "マチカネフクキタル",
            "text": "ぬぬぬぬ～。トレーナーさんの厄よ～、\r\n去れ～、今すぐ去れ～！"
        },
        {
            "name": "",
            "text": "その後、『トレーナーさんに何かあっては\r\n困りますから！』と、オマジナイを\nいくつもかけられつつ帰路についた。"
        }
    ]
}