{
    "title": "ちっちゃな最先端",
    "no_wrap": false,
    "text_block_list": [
        {
            "name": "モノローグ",
            "text": "ワンダーアキュートと出かけた帰り道。\nふと、彼女が思い出したようにこう言った。"
        },
        {
            "name": "ワンダーアキュート",
            "text": "そうだ、トレーナーさん。"
        },
        {
            "name": "ワンダーアキュート",
            "text": "今日はちょこっと寄りたいところが\nあるんだけど、いいかしら？",
            "choice_data_list": [
                "もちろん！"
            ]
        },
        {
            "name": "モノローグ",
            "text": "ワンダーアキュートについていき、\nしばらく歩いた。が――そのうち、\n彼女は足を止めてしまった。",
            "choice_data_list": [
                "ええと……寄りたかった場所って？"
            ]
        },
        {
            "name": "ワンダーアキュート",
            "text": "……どこじゃったかねぇ。",
            "choice_data_list": [
                "え？"
            ]
        },
        {
            "name": "ワンダーアキュート",
            "text": "このへんだったと思ったのよ。\nけど、やっぱり詳しく覚えてなくてねぇ。"
        },
        {
            "name": "ワンダーアキュート",
            "text": "ほら、この間さくらんぼパイの話を\nしたでしょう？"
        },
        {
            "name": "ワンダーアキュート",
            "text": "あれから気になっててね。\nあのお店を探してるのよぉ。"
        },
        {
            "name": "ワンダーアキュート",
            "text": "けど、うぅ～ん……やっぱり\n細かい場所はわからないわねぇ。"
        },
        {
            "name": "モノローグ",
            "text": "なるほど、例のケーキ屋を探しているらしい。\n何か手伝えることはないだろうか……。"
        },
        {
            "name": "？？？",
            "text": "どしたん？\nさっきからずーっとぐるぐるしてっけど。"
        },
        {
            "name": "ワンダーアキュート",
            "text": "あらあ、ジョーダンちゃん。\nそうなのよ、ぐるぐるが止まらないの。"
        },
        {
            "name": "モノローグ",
            "text": "探しているお店がなかなか\n見つからないことを、\nトーセンジョーダンに伝えた。"
        },
        {
            "name": "トーセンジョーダン",
            "text": "ならスマホ使えばよくね？\nえっと、ケーキ屋だっけ。"
        },
        {
            "name": "トーセンジョーダン",
            "text": "マップアプリで……あ～。\nこのへんにケーキ屋、けっこーあんね。"
        },
        {
            "name": "トーセンジョーダン",
            "text": "店のデザインは？\n色とか看板とか……なんか覚えてる？"
        },
        {
            "name": "ワンダーアキュート",
            "text": "えっとねぇ……ああ、そうだ。\nあそこのお店みたいな赤い屋根だった\n気がするねぇ。"
        },
        {
            "name": "トーセンジョーダン",
            "text": "おけ。んじゃ画像検索いっとくか。\nあの屋根、っと――"
        },
        {
            "name": "モノローグ",
            "text": "（パシャ！）"
        },
        {
            "name": "ワンダーアキュート",
            "text": "わぁ、綺麗に撮れたねぇ。\nそれで……その写真をどうするんだい？"
        },
        {
            "name": "トーセンジョーダン",
            "text": "アップすんの。したら\n似たよーなのが出てくんだよね。"
        },
        {
            "name": "トーセンジョーダン",
            "text": "ほら。赤い屋根の店めっちゃ出てきたっしょ？"
        },
        {
            "name": "ワンダーアキュート",
            "text": "わ！！　わわわっ！？\nこんなことできるのぉ！？"
        },
        {
            "name": "ワンダーアキュート",
            "text": "すまほ、すごいねぇ～～！\nちっちゃいのに、えらいねぇ～～！"
        },
        {
            "name": "トーセンジョーダン",
            "text": "わかる！？　そーなんよ！\n他にもめっちゃ機能あってさ～、\nこうやって屋根のとこだけ切り取ったり――"
        },
        {
            "name": "トーセンジョーダン",
            "text": "んで、アキュートさんの写真をこうすっと……\nすっげー変わんの！　ヤバくね！？"
        },
        {
            "name": "ワンダーアキュート",
            "text": "わひゃ～～！！　こりゃ、すごいねえ！！\nあたしの耳が、トナカイさんの角に\nなっちゃった！！"
        },
        {
            "name": "モノローグ",
            "text": "それからしばらくスマホ談義が続いた。\n教えるトーセンジョーダンも、\n教わるワンダーアキュートも楽しそうだ。",
            "choice_data_list": [
                "この機会にスマホに変えてみる？",
                "楽しめたみたいだな",
                "楽しめたみたいだね"
            ]
        },
        {
            "name": "モノローグ",
            "text": "それからしばらくスマホ談義が続いた。\n教えるトーセンジョーダンも、\n教わるワンダーアキュートも楽しそうだ。",
            "choice_data_list": [
                "この機会にスマホに変えてみる？",
                "楽しめたみたいだな",
                "楽しめたみたいだね"
            ]
        },
        {
            "name": "ワンダーアキュート",
            "text": "あたしが、かい？"
        },
        {
            "name": "ワンダーアキュート",
            "text": "ふふ、大丈夫よぉ。今の携帯で\n電話もめーるもできるもの。"
        },
        {
            "name": "ワンダーアキュート",
            "text": "がらけーもね、ちっちゃくてえらいの。\nだから、大丈夫よぉ。"
        },
        {
            "name": "トーセンジョーダン",
            "text": "アキュートさんのメール、\n味があってイイんよね～～。\nそこは変わんねーでほしい感あるわ～！"
        },
        {
            "name": "ワンダーアキュート",
            "text": "ええ。\nすまほって、やっぱりすごいのねぇ～。"
        },
        {
            "name": "ワンダーアキュート",
            "text": "それに、すまほを使うみんなも、\n色々知っててすごいわぁ。"
        },
        {
            "name": "ワンダーアキュート",
            "text": "あたしには難しそうだけれど、\n機会があったらまた聞きたいわねぇ。"
        },
        {
            "name": "トーセンジョーダン",
            "text": "任せろし！\n神機能マスターしとくわ！"
        }
    ]
}