{
    "title": "重なるハイとロー",
    "no_wrap": false,
    "text_block_list": [
        {
            "name": "エアシャカール",
            "text": "――ン、DM……。\r\n……『ビート制作依頼』か。"
        },
        {
            "name": "エアシャカール",
            "text": "（たッま～に来ンだよなァ。\r\n曲投稿してる別名義……『!monad』宛に）"
        },
        {
            "name": "エアシャカール",
            "text": "（曲作りは分析中の手慰み、頭の切り替え……\r\nただそれだけの、趣味とも言えねェ暇つぶし。\n他人の曲作る気はハナからねェ。コレも――）"
        },
        {
            "name": "エアシャカール",
            "text": "ア？　また来た……。\r\n『!monadの自由に制作してください。\n貴方の音に、リリックをのせたいです』"
        },
        {
            "name": "エアシャカール",
            "text": "（自由に……。無償でとか、\r\n安く作らせるための選択じゃない。\n……“オレ”がイイって言いたいわけか？）"
        },
        {
            "name": "エアシャカール",
            "text": "…………全くロジカルじゃねェな。"
        },
        {
            "name": "エアシャカール",
            "text": "（――とは言っても……ラップがのる\r\n前提で作ったことねェしな。\nなンッッもイメージ湧かねェ……）"
        },
        {
            "name": "エアシャカール",
            "text": "（ストックを『っぽく』いじって終わらすか？\r\n適当に仕上がるだろ。だが……）"
        },
        {
            "name": "メイショウドトウ",
            "text": "あの、シャカールさん……。\r\nもうすぐ、消灯ですけどぉ……。"
        },
        {
            "name": "エアシャカール",
            "text": "ン、電気消しとく。\r\nおやすみ。"
        },
        {
            "name": "メイショウドトウ",
            "text": "（……って、シャカールさん、\r\nやっぱり寝てないぃ……。\nずっとPC触って……音楽、聴いてる？）"
        },
        {
            "name": "メイショウドトウ",
            "text": "（この間のレースの後も、そうだったな。\r\nあの時は、シャカールさん……。\n……今日も悩んでるの、かな……）"
        },
        {
            "name": "メイショウドトウ",
            "text": "……私になにか、できないのかなぁ？"
        },
        {
            "name": "モノローグ",
            "text": "ある日、学園を移動していると――"
        },
        {
            "name": "エアシャカール",
            "text": "――だからって……よりにもよって\r\nそいつに声かけるかァ？"
        },
        {
            "name": "メイショウドトウ",
            "text": "で、でも、私の知ってるなかで、\r\n1番音楽に詳しい人って言ったらぁ～……。"
        },
        {
            "name": "テイエムオペラオー",
            "text": "そう！　このボク！\r\nテイエムオペラオーの出番というわけだね！"
        },
        {
            "name": "テイエムオペラオー",
            "text": "『シャカールさんの息抜きになりそうな、\r\n素敵な音楽はないか』……ドトウが問うた時、\nその答えはすぐ目の前にあったのさ！"
        },
        {
            "name": "テイエムオペラオー",
            "text": "さあ、シャカールさん！　選びたまえ！\r\nドトウのエモーショナルなHIPHOP演歌か、\nボクのファビュラスなHIPHOPオペラか！？"
        },
        {
            "name": "エアシャカール",
            "text": "……ハ？\r\nなンだそりゃ。"
        },
        {
            "name": "テイエムオペラオー",
            "text": "シャカールさんがHIPHOP好きと聞いてね！\r\nならばアレンジしてあげようと、\nドトウと取り決めたのさっ！"
        },
        {
            "name": "メイショウドトウ",
            "text": "わ、私もがんばって韻を踏みますぅ……！\r\nだから、シャカールさん……！"
        },
        {
            "name": "エアシャカール",
            "text": "……………………。\r\n…………ハァ。"
        },
        {
            "name": "エアシャカール",
            "text": "オイ、お前。そこのトレーナー。\r\nお前が決めろ。",
            "choice_data_list": [
                "え！？"
            ]
        },
        {
            "name": "エアシャカール",
            "text": "オレたちのこと、ボケッと見てただろ。\r\n好きなほう選べ。オレは決めたくねェ……。",
            "choice_data_list": [
                "HIPHOPオペラ",
                "HIPHOP演歌"
            ]
        },
        {
            "name": "テイエムオペラオー",
            "text": "はーっはっはっ！　まあそうだろうね！\r\n題して……『我が愛しのライム』！\n始めよう！"
        },
        {
            "name": "テイエムオペラオー",
            "text": "我が名はオペラオー！\r\n最高のウマ娘にして至高のウマ娘！"
        },
        {
            "name": "エアシャカール",
            "text": "……ハァ？"
        },
        {
            "name": "テイエムオペラオー",
            "text": "薔薇の香りのオペラオー、\r\nフゥン、かぐわしやラララ～♪\n讃える全ての観客！　ヘンズアップ！！"
        },
        {
            "name": "テイエムオペラオー",
            "text": "――これにてHIPHOPオペラは終幕！\r\n……誘惑ッ！　オーソレミオッッッ！"
        },
        {
            "name": "エアシャカール",
            "text": "……いや、どこがHIPHOPオペラだよ。\r\nどっちの要素も皆無じゃねェか。"
        },
        {
            "name": "テイエムオペラオー",
            "text": "最後に韻を踏んだだろう？\r\n何より、ボクが奏でれば全てオペラなのさ！\nはーっはっはっ！"
        },
        {
            "name": "エアシャカール",
            "text": "定義がザルすぎンだろ――"
        },
        {
            "name": "エアシャカール",
            "text": "……いや、まァ……そうか。\r\nオレが作れば……全部そうなる。\nなら、文字通り自由に……。"
        },
        {
            "name": "テイエムオペラオー",
            "text": "おや、賢者たるシャカールさんに、\r\n叡智を授けたようだね？\nさすがボク……罪なボク！"
        },
        {
            "name": "エアシャカール",
            "text": "……ドトウ。今度、メシ奢るわ。\r\nソイツも連れてこい。口にガムテ貼ってな。"
        },
        {
            "name": "メイショウドトウ",
            "text": "……！\r\nはいっ、シャカールさん……！\n……え、ガムテ？"
        },
        {
            "name": "エアシャカール",
            "text": "……オイ、ドトウ。一応言うが、\r\n無理すンな。大ケガすンぞ。"
        },
        {
            "name": "メイショウドトウ",
            "text": "で、でも……私……がんばりたいんです！\r\nMCドトウ、いきますぅ……！"
        },
        {
            "name": "メイショウドトウ",
            "text": "……よっ、よぉ～っ♪\r\n私の韻、ベタ踏み、アクセル、全開ぃぃ～♪\nはあぁぁ～ん♪"
        },
        {
            "name": "メイショウドトウ",
            "text": "え～とぉ～♪　あ、アイス～、\r\nす、すみれ～……かえる～……♪\nふんふんふふ～ん……♪"
        },
        {
            "name": "エアシャカール",
            "text": "……！\r\nオイ、今のメロディ……。"
        },
        {
            "name": "メイショウドトウ",
            "text": "あ！　えっと……シャカールさん、\r\nたまに音漏れしてるから……そこから、\n曲、調べちゃって……す、すみません。"
        },
        {
            "name": "メイショウドトウ",
            "text": "でも、好きなもののお話し相手になれたら、\r\nシャカールさんの気分も、\n少しは休まるかなって……。"
        },
        {
            "name": "エアシャカール",
            "text": "ドトウ……。"
        },
        {
            "name": "エアシャカール",
            "text": "……こンなトンチキ演歌聞かされたら、\r\n肩の力も気も抜けるわ。\nついでに詰まってたモンもな。"
        },
        {
            "name": "メイショウドトウ",
            "text": "……！\r\nしゃ、シャカールさぁん～！"
        },
        {
            "name": "テイエムオペラオー",
            "text": "シャカールさんは悩んでいたのか！\r\nであればボクも閃きを授けてあげよう！\n『オペラオーの凱旋』、ご堪能あれ！"
        },
        {
            "name": "エアシャカール",
            "text": "マジでいらねェ。"
        }
    ]
}