{
    "title": "夏合宿（2年目）終了",
    "no_wrap": false,
    "text_block_list": [
        {
            "name": "モノローグ",
            "text": "夏合宿中のある時点から、\n心のモヤが晴れたかのように\nすっきりした顔をしていたスティルインラブ。"
        },
        {
            "name": "モノローグ",
            "text": "メンタル面の上下が小さくなったからか、\nその後は本能が暴走することも少なくなり、\n非常にいい状態で最終日を迎えられた。",
            "choice_data_list": [
                "（『秋華賞』も、今のスティルなら……！）"
            ]
        },
        {
            "name": "スティルインラブ",
            "text": "……ふふ。"
        },
        {
            "name": "スティルインラブ",
            "text": "トレーナーさんがお嬉しそうで、\n何よりです。",
            "choice_data_list": [
                "……なんだか、自信に満ち溢れてるな",
                "……なんだか、自信に満ち溢れてるね"
            ]
        },
        {
            "name": "スティルインラブ",
            "text": "えっ。\nそ、そうでしょうか……？"
        },
        {
            "name": "スティルインラブ",
            "text": "ですが……はい。"
        },
        {
            "name": "スティルインラブ",
            "text": "『オークス』以上の走りをお見せする……\nお約束は、できます。"
        },
        {
            "name": "スティルインラブ",
            "text": "――トリプルティアラは、目の前……ですね。"
        },
        {
            "name": "モノローグ",
            "text": "鼓動が高鳴る。彼女ならば、本当に……\n成し得るのかもしれない。",
            "choice_data_list": [
                "（史上2人目の、トリプルティアラを――）"
            ]
        },
        {
            "name": "アドマイヤグルーヴ",
            "text": "――はああああああああ……！！"
        },
        {
            "name": "アドマイヤグルーヴ",
            "text": "ふうっ……ふうっ……。\n……っぐ……！"
        },
        {
            "name": "アドマイヤグルーヴ",
            "text": "まだよ……まだ、足りない……！\nもっと……もっと、走るの……――"
        },
        {
            "name": "アドマイヤグルーヴ",
            "text": "でないと……。\n……――なくなっちゃう……。"
        },
        {
            "name": "アドマイヤグルーヴ",
            "text": "私に……なにも……――\n……っぁ……。"
        },
        {
            "name": "モノローグ",
            "text": "（ドサッ……）"
        },
        {
            "name": "？？？",
            "text": "こいつ、本当にちゃんと食べているのか？\n全く……世話の焼ける奴め……。"
        },
        {
            "name": "アドマイヤグルーヴ",
            "text": "……ん……。\n………………あったかい……――"
        },
        {
            "name": "アドマイヤグルーヴ",
            "text": "――……。"
        },
        {
            "name": "アドマイヤグルーヴ",
            "text": "……え……。"
        },
        {
            "name": "エアグルーヴ",
            "text": "起きたか。\n……具合は？"
        },
        {
            "name": "アドマイヤグルーヴ",
            "text": "エアグルーヴさん……。\n私……？"
        },
        {
            "name": "エアグルーヴ",
            "text": "ビーチで倒れていたんだ。\n追い込みすぎだな。"
        },
        {
            "name": "エアグルーヴ",
            "text": "合宿所と学園には連絡済みだ。\nしばらくここで休め。"
        },
        {
            "name": "アドマイヤグルーヴ",
            "text": "……ご迷惑をおかけしました。\nでも、もう平気……。"
        },
        {
            "name": "エアグルーヴ",
            "text": "また走りに戻るのか？\n今度は倒れるだけでは\n済まないかもしれない。"
        },
        {
            "name": "アドマイヤグルーヴ",
            "text": "いいです、別に。\nそれなら、それで……構いません。"
        },
        {
            "name": "エアグルーヴ",
            "text": "構わないというのは、\n今後一切走れなくなってもいいということか？"
        },
        {
            "name": "アドマイヤグルーヴ",
            "text": "……っ。\nうるさい……。"
        },
        {
            "name": "アドマイヤグルーヴ",
            "text": "貴方には関係ないでしょう！\nもう口を出さないで――"
        },
        {
            "name": "エアグルーヴ",
            "text": "たわけが！"
        },
        {
            "name": "アドマイヤグルーヴ",
            "text": "……っ！？"
        },
        {
            "name": "エアグルーヴ",
            "text": "お前は走るためにここに来たのだろう。\nなのに自暴自棄になって、無茶苦茶をして――"
        },
        {
            "name": "エアグルーヴ",
            "text": "走ることを、\n己を追い詰める道具にするな！"
        },
        {
            "name": "アドマイヤグルーヴ",
            "text": "……そ、そんなつもりじゃ。\n私は……ただ……。"
        },
        {
            "name": "エアグルーヴ",
            "text": "勝ちたいのだろう？\n己の信じるものを証明するために。\nだったら、努力の方向を間違えるな。"
        },
        {
            "name": "エアグルーヴ",
            "text": "もっと……自分を大切にしろ。\nなぜ、そんな簡単なことができない……。"
        },
        {
            "name": "アドマイヤグルーヴ",
            "text": "エアグルーヴさん……？"
        },
        {
            "name": "エアグルーヴ",
            "text": "……お前が倒れているのを見つけて、\n心臓が止まるかと思った。"
        },
        {
            "name": "モノローグ",
            "text": "（ギュッ……）"
        },
        {
            "name": "アドマイヤグルーヴ",
            "text": "！\nあ……。"
        },
        {
            "name": "エアグルーヴ",
            "text": "……本当に、世話の焼ける奴め。"
        },
        {
            "name": "アドマイヤグルーヴ",
            "text": "…………あったかい……。"
        },
        {
            "name": "アドマイヤグルーヴ",
            "text": "これが……。"
        },
        {
            "name": "アドマイヤグルーヴ",
            "text": "愛、なの？"
        },
        {
            "name": "アドマイヤグルーヴ",
            "text": "……っ。\n――……嫌。"
        },
        {
            "name": "アドマイヤグルーヴ",
            "text": "なくていい。こんなに、\nあったかいもの……いらない……！"
        },
        {
            "name": "アドマイヤグルーヴ",
            "text": "……なんの意味も、ないの。\nそうでしょう？　……でないと――"
        },
        {
            "name": "アドマイヤグルーヴ",
            "text": "――私は、空っぽなんかじゃない……。"
        },
        {
            "name": "スティルインラブ",
            "text": "……ふ、ふ……♪\nふ、ふ、ふ……♪"
        },
        {
            "name": "ネオユニヴァース",
            "text": "スティルインラブは、\n『ごきげん』？"
        },
        {
            "name": "ネオユニヴァース",
            "text": "夏合宿は……“クエーサー”。\n『成長』、できたんだね。"
        },
        {
            "name": "スティルインラブ",
            "text": "そうですね……。\nこれで、『秋華賞』にも……堂々と臨めます。"
        },
        {
            "name": "ネオユニヴァース",
            "text": "トリプルティアラ――\nスティルインラブに、よく似合うね。"
        },
        {
            "name": "スティルインラブ",
            "text": "……そ、そう思いますか？\n……ふふ。"
        },
        {
            "name": "スティルインラブ",
            "text": "ユニヴァースさんも、\n『菊花賞』を勝てば……。"
        },
        {
            "name": "スティルインラブ",
            "text": "クラシック三冠達成、ですね。\n史上6人目の……。"
        },
        {
            "name": "スティルインラブ",
            "text": "……ふふ。同世代の、同室ふたりが……\nどちらも偉業を成せたら……すごい。"
        },
        {
            "name": "スティルインラブ",
            "text": "貴方は冠。私はティアラを……\n一緒に、戴けるとよいですね。"
        },
        {
            "name": "ネオユニヴァース",
            "text": "……――"
        },
        {
            "name": "ネオユニヴァース",
            "text": "そうなったら、\nよかったのにね。"
        },
        {
            "name": "スティルインラブ",
            "text": "？\nそう、なったら……？"
        },
        {
            "name": "ネオユニヴァース",
            "text": "それは定められた、『運命』だから。"
        },
        {
            "name": "ネオユニヴァース",
            "text": "ネオユニヴァースは――\n辿るべき運命が決まっている。"
        },
        {
            "name": "ネオユニヴァース",
            "text": "“シンギュラリティ”が、ないから。"
        },
        {
            "name": "ネオユニヴァース",
            "text": "“DTFT”。あなたは……\n“軌道”を変えられる。"
        },
        {
            "name": "ネオユニヴァース",
            "text": "“それ”が変われば、全てが変わる。\nふたりの『しあわせ』を願うよ。"
        },
        {
            "name": "スティルインラブ",
            "text": "……？\n……。"
        },
        {
            "name": "スティルインラブ",
            "text": "なら、私も……ユニヴァースさんの、\n幸せを……お祈りします。"
        },
        {
            "name": "スティルインラブ",
            "text": "貴方が、貴方らしく……\n幸せで、ありますように……。"
        },
        {
            "name": "ネオユニヴァース",
            "text": "……スフィーラ。"
        },
        {
            "name": "モノローグ",
            "text": "夏合宿は終わり――いよいよ、\n最後のひとつ……『秋華賞』が来る。"
        }
    ]
}