{
    "title": "草野球でエール！",
    "no_wrap": false,
    "text_block_list": [
        {
            "name": "ナイスネイチャ",
            "text": "会場、ここ？\r\nおー、確かに人が集まってますなー。"
        },
        {
            "name": "ナイスネイチャ",
            "text": "しっかし、草野球の助太刀なんて\r\nよく引き受けたね……。\nただでさえトレーナー業が忙しそうなのに。"
        },
        {
            "name": "モノローグ",
            "text": "実は数日前、商店街の人たちに声をかけられ\r\n草野球の試合に参加することとなった。",
            "choice_data_list": [
                "いつもネイチャを応援してもらってるし"
            ]
        },
        {
            "name": "ナイスネイチャ",
            "text": "いやまあ、たしかにみなさんには\r\nよくしてもらっていますけど……。"
        },
        {
            "name": "ナイスネイチャ",
            "text": "……でも、あー……張り切りすぎて\r\nケガとかはやめてくださいよー？"
        },
        {
            "name": "ナイスネイチャ",
            "text": "ただでさえ、\r\n普段から頑張りすぎなんだから……。"
        },
        {
            "name": "モノローグ",
            "text": "こうして、ついに商店街対抗草野球の\r\n戦いの幕が上がった！"
        },
        {
            "name": "モノローグ",
            "text": "両チームとも一歩も譲らず、\r\n0対0のまま試合はヒートアップしていく。"
        },
        {
            "name": "ナイスネイチャ",
            "text": "いやはや、白熱してますなぁ～。\r\n……てか、トレーナーさんバテバテじゃん。"
        },
        {
            "name": "ナイスネイチャ",
            "text": "ひいき目なしに、かなり頑張ってるし、\r\nそろそろ誰かに交代してもらっても\nいいと思うんだけど。",
            "choice_data_list": [
                "まだやれる……！"
            ]
        },
        {
            "name": "ナイスネイチャ",
            "text": "いや、熱血か。\r\n……って、そうか。アタシがお世話に\nなってるぶん、頑張ってるんだっけ。"
        },
        {
            "name": "ナイスネイチャ",
            "text": "ホラ、なんか飲むもの取ってくるんで\r\n大人しく座っててくださいよー？"
        },
        {
            "name": "ナイスネイチャ",
            "text": "まったくもう……\r\nえーと、実行委員会のテントは……。"
        },
        {
            "name": "商店街のおじさん",
            "text": "いやー、あとちょっとなんだがなあ。\n頑張ってくれてるんだが、\nなかなか点につながらない……。"
        },
        {
            "name": "ナイスネイチャ",
            "text": "（お、トレーナーさんの話してる……？）"
        },
        {
            "name": "商店街のおばさん",
            "text": "やっぱり緊張してるのかしらねえ。\n助っ人ってことで、知らないメンバーに\n囲まれてるわけだし……。"
        },
        {
            "name": "商店街のおじさん",
            "text": "う～む……\n何とかこう、元気づけてやれないもんかなあ。"
        },
        {
            "name": "ナイスネイチャ",
            "text": "（……なんか、\r\n聞き覚えのある話……というか）"
        },
        {
            "name": "商店街の人々",
            "text": "ネイちゃーん！！　いけっ、そこだー！！\nがんばれー、ネイちゃーん！！"
        },
        {
            "name": "ナイスネイチャ",
            "text": "『あなたというウマ娘に出会えたことが、\n私たちにとってかけがえのない宝物です』"
        },
        {
            "name": "ナイスネイチャ",
            "text": "（アタシが頑張るぞって時に\r\n背中を押してくれたのは、\nみんなとトレーナーさんなんだよねぇ……）"
        },
        {
            "name": "ナイスネイチャ",
            "text": "（なら心配するばっかりじゃなくて、\r\n今度はアタシが――）"
        },
        {
            "name": "モノローグ",
            "text": "ついに迎えた9回裏。\n一打出ればサヨナラという状況で\n打順が自分に回ってきた。"
        },
        {
            "name": "モノローグ",
            "text": "目の前のマウンドに立つのは、\n甲子園にベンチで出場した経験もあるという\n豪腕を誇るおじさんだ。"
        },
        {
            "name": "モノローグ",
            "text": "既にツーストライクまで追い込まれ、\r\nもはやこれまでか――そう思った、その時。"
        },
        {
            "name": "？？？",
            "text": "頑張れーっ！"
        },
        {
            "name": "ナイスネイチャ",
            "text": "負けるな、トレーナーさーん！\r\nあと一打！　ここ打ったら勝てるっ！"
        },
        {
            "name": "ナイスネイチャ",
            "text": "元気、出ろ！　出せ！\r\nみんなーっ、せーの！"
        },
        {
            "name": "商店街のみなさん",
            "text": "イエーイ！　Go Fight Win！"
        },
        {
            "name": "ナイスネイチャ",
            "text": "が、頑張れ！　トレーナーさーんっ！"
        },
        {
            "name": "モノローグ",
            "text": "照れながらも応援をくれるナイスネイチャ。\r\nそして周りの人たち。\nここはなんとしても応援に応えなければ……！",
            "choice_data_list": [
                "でやああーーっ！！"
            ]
        },
        {
            "name": "ナイスネイチャ",
            "text": "いっけーーっ！！"
        },
        {
            "name": "モノローグ",
            "text": "（カッキーーン！）"
        },
        {
            "name": "ナイスネイチャ",
            "text": "やった～っ！　やりおった！\nやるじゃんトレーナーさん！\nホームラン！　サヨナラ勝ちだ！",
            "choice_data_list": [
                "応援、本当にありがとう！"
            ]
        },
        {
            "name": "ナイスネイチャ",
            "text": "うぐっ……。\r\nそうキラキラ見つめられると\nなんか照れるな～……。"
        },
        {
            "name": "ナイスネイチャ",
            "text": "……ありがとう、って言うのは\r\nわりとこちらのほうでして。こちらこそ、\nいつも応援アリガトーゴザイマス。"
        },
        {
            "name": "ナイスネイチャ",
            "text": "まあ、これからも頑張っていこーって\r\nコトで……か～っ、\nガラにもないこと言っちゃったわ、もー！"
        },
        {
            "name": "モノローグ",
            "text": "恥ずかしがりながらも、\r\n心からの応援を見せてくれたナイスネイチャ。\nかけがえのない思い出となった1日だった！"
        },
        {
            "name": "ナイスネイチャ",
            "text": "……おしっ。\r\nやるじゃん、トレーナーさん。お疲れ！",
            "choice_data_list": [
                "ネイチャの応援のおかげだ！",
                "ネイチャの応援のおかげだよ！"
            ]
        },
        {
            "name": "ナイスネイチャ",
            "text": "いやいや、そんなそんな。\r\nトレーナーさんの努力と実力の賜物ですって。\nまあ、でも……。"
        },
        {
            "name": "ナイスネイチャ",
            "text": "トレーナーさん、なかなか応援しがいが\r\nあるじゃん。また野球する時は\n応援しに行こうかなー……なんてね。"
        },
        {
            "name": "モノローグ",
            "text": "恥ずかしそうに視線を逸らすナイスネイチャ。\r\nしかし彼女との絆を確かに感じた、\nすばらしい1日だった！"
        },
        {
            "name": "ナイスネイチャ",
            "text": "はあ～あ、恥ずかしかった～！\r\nネイチャさん、\nホントにこーゆーのガラじゃないわ！",
            "choice_data_list": [
                "ネイチャー！ありがとうー！"
            ]
        },
        {
            "name": "ナイスネイチャ",
            "text": "ゲッ、大声出さないでくださいよー、\r\nこっちに注目が集まるじゃん！\nもー着替えてきますから！"
        },
        {
            "name": "ナイスネイチャ",
            "text": "……ま、力になれたならよかったですケド。"
        },
        {
            "name": "モノローグ",
            "text": "まだまだ素直になれないナイスネイチャ。\r\nしかし彼女の想いを確かに感じた、\n貴重な1日だった！"
        }
    ]
}