{
    "title": "温泉旅行",
    "no_wrap": false,
    "text_block_list": [
        {
            "name": "",
            "text": "サウンズオブアースとたくさんのレースを\n勝ち抜いてきた、ある日のこと。"
        },
        {
            "name": "サウンズオブアース",
            "text": "――オー・ソレ・ミオ！！"
        },
        {
            "name": "サウンズオブアース",
            "text": "トレーナー！\nついにこの時がやって来たね！",
            "choice_data_list": [
                "……この時？"
            ]
        },
        {
            "name": "サウンズオブアース",
            "text": "スィ！　いつか約束しただろう？\n未来の私たちへのご褒美を。"
        },
        {
            "name": "",
            "text": "そういえば、福引で温泉旅行券を\n手に入れた時、そんな話をしたはずだ。"
        },
        {
            "name": "サウンズオブアース",
            "text": "レースに一区切りがついた今――\nその頃合いだと思うんだ。どうかな？"
        },
        {
            "name": "",
            "text": "これまで2人で必死に進み続けてきた。\n彼女の言うとおり、そろそろ\n休息を取ってもいいのかもしれない。",
            "choice_data_list": [
                "ああ、そうしよう！",
                "うん、そうしよう！"
            ]
        },
        {
            "name": "",
            "text": "こうして、後日――"
        },
        {
            "name": "サウンズオブアース",
            "text": "コモドでトランクィッロな雰囲気……\nふふ、とても落ち着くね。"
        },
        {
            "name": "サウンズオブアース",
            "text": "温泉があるというのもまたアジアタメンテ。\nよければトレーナー、先に入っておいで。",
            "choice_data_list": [
                "いいのか？",
                "いいの？"
            ]
        },
        {
            "name": "サウンズオブアース",
            "text": "ああ。私はいつものエチュードを\nしておきたくてね。遠慮しないで。"
        },
        {
            "name": "",
            "text": "それならばと、\n一足先に温泉に入ることにした。"
        },
        {
            "name": "サウンズオブアース",
            "text": "（――さて、これで準備は完了かな？）"
        },
        {
            "name": "サウンズオブアース",
            "text": "（トレーナー……3年間積み重ねてきた\n君への想いを今、伝えようと思う）"
        },
        {
            "name": "サウンズオブアース",
            "text": "（どうか、君の心に響きますように――）"
        },
        {
            "name": "",
            "text": "露天風呂に浸かり、夜空を眺める。\n綺麗な景色に、温泉の温かさ……\n心地いい安堵感を覚えていた時――"
        },
        {
            "name": "",
            "text": "（――……♪）"
        },
        {
            "name": "",
            "text": "不意にヴァイオリンの音色が聞こえてきた。\nかと思うと――"
        },
        {
            "name": "サウンズオブアース",
            "text": "LaLaLaLaLa～～……♪",
            "choice_data_list": [
                "（この歌声は……アース？）"
            ]
        },
        {
            "name": "",
            "text": "どういうことだろうかと、\n最初は疑問に思ったが――"
        },
        {
            "name": "",
            "text": "いつになく優しげな歌声に、\n疑問は気にならなくなった。柔らかい振動は、\n温泉の香りと共に体に染み込んでいく……。",
            "choice_data_list": [
                "（なんだか癒されるなあ……）"
            ]
        },
        {
            "name": "",
            "text": "ぼんやりと夢見心地の状態で、\n温泉から上がる。すると、\nサウンズオブアースが待っていた。"
        },
        {
            "name": "サウンズオブアース",
            "text": "その表情……どうやら\nアダージョな気分になれたみたいだね。"
        },
        {
            "name": "サウンズオブアース",
            "text": "ふふ、君のための\nリサイタルは成功したようだ。",
            "choice_data_list": [
                "リサイタル……？"
            ]
        },
        {
            "name": "サウンズオブアース",
            "text": "――スィ。"
        },
        {
            "name": "サウンズオブアース",
            "text": "……ずっと、君に伝えたいと思っていた。\nありのままの感謝を、私の心を。"
        },
        {
            "name": "サウンズオブアース",
            "text": "これまでの日々……君には\nたくさんの苦労をかけてしまったね。"
        },
        {
            "name": "サウンズオブアース",
            "text": "時には不安にさせてしまったり、\n重圧を感じさせてしまったこともあると思う。"
        },
        {
            "name": "サウンズオブアース",
            "text": "けれどそんな日々の中でも、\n君といればたくさんの音と出会えた。"
        },
        {
            "name": "サウンズオブアース",
            "text": "その感謝を伝えたくて――\nこの3年間、君のために曲を作り、\nそれを今日、演奏させてもらったんだ。",
            "choice_data_list": [
                "じゃあ、さっきの曲は君が……！？",
                "じゃあ、さっきの曲は貴方が……！？"
            ]
        },
        {
            "name": "サウンズオブアース",
            "text": "ふふ、多少拙い部分もあったと思うけれどね。\n君への想いは存分に込めたつもりさ。"
        },
        {
            "name": "サウンズオブアース",
            "text": "……どうだろう？\n私の曲は気に入ってもらえたかな？"
        },
        {
            "name": "",
            "text": "先ほどの気持ちを思い出す。\nおだやかな旋律に、優しい歌声。\n返事はもちろん――",
            "choice_data_list": [
                "ああ！素敵な曲だった！",
                "うん！素敵な曲だったよ！"
            ]
        },
        {
            "name": "サウンズオブアース",
            "text": "――ベネ！"
        },
        {
            "name": "サウンズオブアース",
            "text": "……君の心にアルペジオ。\n演奏したかいがあったよ。本当に……。"
        },
        {
            "name": "",
            "text": "わざわざ曲を作ってくれたこと、\nそれをさりげなく演奏してくれたこと――\n彼女の心遣いは十分に伝わったのだった。"
        },
        {
            "name": "",
            "text": "入浴中……。"
        },
        {
            "name": "サウンズオブアース",
            "text": "――さて！"
        },
        {
            "name": "サウンズオブアース",
            "text": "心地いい温泉に浸かり、\n素晴らしい食事も終えることができた！"
        },
        {
            "name": "サウンズオブアース",
            "text": "ならば次にすることは……\n1つしかないね、トレーナー？"
        },
        {
            "name": "",
            "text": "食事の後、大広間へ案内されたのだが――\n何をするかはまだ聞いていない。",
            "choice_data_list": [
                "え……？なんだろう？"
            ]
        },
        {
            "name": "サウンズオブアース",
            "text": "勿論、セッションさ！"
        },
        {
            "name": "サウンズオブアース",
            "text": "大広間を借りたのもそのためだよ。\n楽器をたくさん持ってきたから、\n好きなものを選んでおくれ！",
            "choice_data_list": [
                "えっと、じゃあ――"
            ]
        },
        {
            "name": "",
            "text": "彼女が持ってきてくれた\nカスタネットに手を伸ばし、鳴らした。"
        },
        {
            "name": "",
            "text": "（シャカシャカシャカシャカ！！）\n（カチカチカチカチッ！！）"
        },
        {
            "name": "",
            "text": "小気味いいリズムが響き渡る。\nカスタネットを奏でるたび、\n自分の心も高揚していくのを感じた……！"
        },
        {
            "name": "",
            "text": "そうしているうち――"
        },
        {
            "name": "好奇心旺盛な宿泊客",
            "text": "……ん？　なんだろう？\n催し物でもやってるのかな？　面白そう！"
        },
        {
            "name": "サウンズオブアース",
            "text": "――！\n予期せぬお客人の登場だ……！"
        },
        {
            "name": "サウンズオブアース",
            "text": "私たちの音が彼らの心に響いたようだね。\n是非とも聞かせてあげようじゃないか、\nトレーナー！",
            "choice_data_list": [
                "ああ、そうだな！",
                "うん、そうだね！"
            ]
        },
        {
            "name": "サウンズオブアース",
            "text": "――皆様、さあさあどうぞこちらへ！\n私たちのセッションを心ゆくまでご堪能あれ！"
        },
        {
            "name": "",
            "text": "それから、様々な楽器を使って演奏を続けた。\n宿泊客たちに加え、やがて従業員たちも\n鑑賞に来て、楽しい音楽会になったのだった。"
        },
        {
            "name": "サウンズオブアース",
            "text": "人々の期待に満ちた瞳、弾む鼓動――\nふふ、今日も新しいサウンドに出会えたね。"
        },
        {
            "name": "サウンズオブアース",
            "text": "これからも、君と一緒にあらゆる音を\n聴いていきたい。どうかな……\n……私のディレットレ？",
            "choice_data_list": [
                "ああ、よろしく！",
                "うん、よろしくね！"
            ]
        },
        {
            "name": "サウンズオブアース",
            "text": "これからも、君と一緒にあらゆる音を\n聴いていきたい。どうかな……\n……私のディレットリチェ？",
            "choice_data_list": [
                "ああ、よろしく！",
                "うん、よろしくね！"
            ]
        },
        {
            "name": "",
            "text": "サウンズオブアースとの間に、\nかけがえのない絆を感じた\nひとときだった……。"
        }
    ]
}