{
    "title": "わからされる本能",
    "no_wrap": false,
    "text_block_list": [
        {
            "name": "通行人A",
            "text": "た、大変だーー！！\n興奮したピットブルが逃げ出したぞー！！"
        },
        {
            "name": "ピットブル",
            "text": "ゴァウッ！！　ガウガァウッ！！"
        },
        {
            "name": "ジェンティルドンナ",
            "text": "あら、おかわいい。"
        },
        {
            "name": "ピットブル",
            "text": "ガルゥッ！！　グルゥルルル！！"
        },
        {
            "name": "ジェンティルドンナ",
            "text": "ふふ。私に牙を剥くなんて、\n威勢がよくてよ。けど――"
        },
        {
            "name": "ジェンティルドンナ",
            "text": "ここは公園……もう少し慎みなさい？"
        },
        {
            "name": "ピットブル",
            "text": "キャイン！？　ク、クゥゥゥン……。"
        },
        {
            "name": "ジェンティルドンナ",
            "text": "ほほほ。聞き分けのいい子ね。"
        },
        {
            "name": "通行人A",
            "text": "あ、あれだけ暴れていたピットブルが\nまるで別犬みたいに……！？"
        },
        {
            "name": "モノローグ",
            "text": "……この件で足止めを食らったため、\nジェンティルドンナは、トレーニングの\n時間に間に合わなかったのだった。"
        }
    ]
}