{
    "title": "すごい顔のドゥラメンテ",
    "no_wrap": false,
    "text_block_list": [
        {
            "name": "ウマ娘A",
            "text": "ドゥ、ドゥラメンテさんっ！\n1個聞いてもいいですか……！？"
        },
        {
            "name": "ウマ娘A",
            "text": "最近、1番奥のトレーニングマシーン\n使ってますよね？\nあそこ夜になるとお化けが出るって噂、で――"
        },
        {
            "name": "ウマ娘A",
            "text": "ひいぃっ！？　つ、つまらない話振って\nすみませんでした～！！"
        },
        {
            "name": "ドゥラメンテ",
            "text": "………………。\n………………。",
            "choice_data_list": [
                "すごい顔してるけど……どうしたんだ？",
                "すごい顔してるけど……どうしたの？"
            ]
        },
        {
            "name": "ドゥラメンテ",
            "text": "……奥のマシンを使うのは、しばらく控える。"
        }
    ]
}