{
    "title": "その血にまつわる",
    "no_wrap": false,
    "text_block_list": [
        {
            "name": "トレーナーの手記",
            "text": "アスリート一族に生まれたドゥラメンテは、\n豊かな才能を受け継いでいた。"
        },
        {
            "name": "トレーナーの手記",
            "text": "彼女は両親を理想とし、幼い頃から\nひたむきにトレーニングに励んできたという。"
        },
        {
            "name": "トレーナーの手記",
            "text": "しかし彼女自身は、自分はまだ\n両親の強さには遠く及ばないと考えていた。"
        },
        {
            "name": "トレーナーの手記",
            "text": "もう1人、彼女が憧れるウマ娘がいる。\n“女帝”エアグルーヴ――ドゥラメンテとは\n昔、同じレーススクールで学んだ仲だ。"
        },
        {
            "name": "トレーナーの手記",
            "text": "ご両親もエアグルーヴも、\nドゥラメンテに期待してくれている。\n応えるためにも、必ず勝たなければ。"
        }
    ]
}