{
    "title": "I'm With You♡",
    "no_wrap": false,
    "text_block_list": [
        {
            "name": "",
            "text": "『宝塚記念』に向けて、\nヴィブロスは更にトレーニングを積んでいた。"
        },
        {
            "name": "ヴィブロス",
            "text": "ねえ、トレっち、\nどうかな？",
            "choice_data_list": [
                "そうだな……",
                "そうだね……"
            ]
        },
        {
            "name": "ヴィブロス",
            "text": "どきどき。",
            "choice_data_list": [
                "負荷を上げようか！"
            ]
        },
        {
            "name": "ヴィブロス",
            "text": "やった～！"
        },
        {
            "name": "ヴィブロス",
            "text": "ベンチプレス、\n重量足してきまーす♡"
        },
        {
            "name": "",
            "text": "ヴィブロスはメンタル的にも安定し、\n体も成長してきた。体調にはまだまだ\n気をつけなければならないが……。"
        },
        {
            "name": "姉妹の母親",
            "text": "――あら！\nうちの子、いい感じなんですね～。",
            "choice_data_list": [
                "！？"
            ]
        },
        {
            "name": "姉妹の父親",
            "text": "こんにちは、トレーナーさん！\nトレーニング中、お邪魔します！"
        },
        {
            "name": "ヴィブロス",
            "text": "あれぇっ！　ママとパパ～！？\nどうしたの？"
        },
        {
            "name": "姉妹の父親",
            "text": "久しぶりだな、ヴィブロス！\n――差し入れ、持ってきたぞ！"
        },
        {
            "name": "ヴィルシーナ",
            "text": "ヴィブロス、\nこっちよ。"
        },
        {
            "name": "ヴィブロス",
            "text": "お姉ちゃんまで！"
        },
        {
            "name": "姉妹の父親",
            "text": "補食用の、あんパンやおにぎり……\nうちの球団のトレーナーから教わって、\nよさそうなのを持ってきたぞ！"
        },
        {
            "name": "姉妹の父親",
            "text": "あとうちのスタジアムの、\n名物グルメも！"
        },
        {
            "name": "姉妹の母親",
            "text": "私も、貴方の大好きなお料理を持ってきたの。\n食べたら元気が出ると思って！"
        },
        {
            "name": "姉妹の母親",
            "text": "トレーナーさん、どれを選ぶかは\nヴィブロスちゃんと貴方の判断に任せるね。",
            "choice_data_list": [
                "はい、ありがとうございます"
            ]
        },
        {
            "name": "ヴィブロス",
            "text": "ねえねえ、\nちょーうれしい！"
        },
        {
            "name": "ヴィブロス",
            "text": "うれしいんだけど……\n急にどうしたの？"
        },
        {
            "name": "姉妹の母親",
            "text": "ママたちも何かしたいって思ったの～。\n貴方たちの『ヴィクトリアマイル』を見て――"
        },
        {
            "name": "姉妹の母親",
            "text": "2人とも、お互いがお互いを高め合う\nレースを見せてくれたでしょう。"
        },
        {
            "name": "姉妹の母親",
            "text": "ママもね、一応レースに出てたから……\n2人がどれほどすごいのかわかるよ。\nどれほど頑張ったのかも……。"
        },
        {
            "name": "姉妹の母親",
            "text": "なのにママたちったら、\nお仕事ばっかりで……。"
        },
        {
            "name": "姉妹の父親",
            "text": "――子どもたちがこれほど成長してるのに、\n近くで見守れないなんてもったいない！"
        },
        {
            "name": "姉妹の父親",
            "text": "『秋華賞』の時みたいに、\n君たちをもっと近くで見ていたい！"
        },
        {
            "name": "姉妹の父親",
            "text": "遅くなってすまない！　だが……\n頑張る君たちの力にならせてくれ！"
        },
        {
            "name": "ヴィブロス",
            "text": "ママ、パパ……。"
        },
        {
            "name": "ヴィルシーナ",
            "text": "2人とも、これからお仕事の合間を\n縫ってなるべく様子を見に来てくれるって。"
        },
        {
            "name": "ヴィルシーナ",
            "text": "私も、この後の目標は特にないし……\n貴方たちのサポートをするわ。"
        },
        {
            "name": "ヴィブロス",
            "text": "……それって。"
        },
        {
            "name": "ヴィブロス",
            "text": "しばらく家族みんなで、\nいっしょにいられるってこと！？"
        },
        {
            "name": "ヴィルシーナ",
            "text": "ええ、そうよ。"
        },
        {
            "name": "ヴィブロス",
            "text": "……～～～～っ。"
        },
        {
            "name": "ヴィブロス",
            "text": "シュヴァちは！？\nここにいないの？"
        },
        {
            "name": "ヴィルシーナ",
            "text": "あの子は別々がいいって。\nでもね、大丈夫よ。"
        },
        {
            "name": "ヴィルシーナ",
            "text": "これ、預かってるもの。"
        },
        {
            "name": "",
            "text": "ヴィルシーナがヴィブロスに渡したのは、\n釣り上げた魚がモチーフになっている、\nかわいらしいチャームだった。"
        },
        {
            "name": "ヴィブロス",
            "text": "これって……――"
        },
        {
            "name": "ヴィブロス",
            "text": "ねえねえ、あのチャームかわいくない？\nおそろしよーよ、シュヴァち♡"
        },
        {
            "name": "シュヴァルグラン",
            "text": "しない……。"
        },
        {
            "name": "ヴィブロス",
            "text": "……えへへ。\nそっか！"
        },
        {
            "name": "ヴィブロス",
            "text": "みんな、\n私のためにありがとう！"
        },
        {
            "name": "ヴィブロス",
            "text": "私、絶対にみんなのこと、\n笑顔にするからね！"
        },
        {
            "name": "ヴィブロス",
            "text": "……ねぇトレっち、\nお願いがあるんだけど！"
        },
        {
            "name": "シュヴァルグラン",
            "text": "――……ぷはぁ。"
        },
        {
            "name": "シュヴァルグラン",
            "text": "あ、これおいしい……。"
        },
        {
            "name": "シュヴァルグラン",
            "text": "……母さんたち、\n僕の分まで……いいのに。",
            "choice_data_list": [
                "シュヴァルグラン"
            ]
        },
        {
            "name": "シュヴァルグラン",
            "text": "っ。"
        },
        {
            "name": "シュヴァルグラン",
            "text": "あ、ヴィブロスの……。\n……えっと、な、何か……？",
            "choice_data_list": [
                "ヴィブロスから差し入れを預かってる"
            ]
        },
        {
            "name": "シュヴァルグラン",
            "text": "ヴィブロスから……？"
        },
        {
            "name": "ヴィブロス",
            "text": "これ、シュヴァちに渡しておいて！"
        },
        {
            "name": "ヴィブロス",
            "text": "これね、激レアクルーズのチケットなの！\nちょーがんばってとったんだ！"
        },
        {
            "name": "ヴィブロス",
            "text": "1人でも楽しめる雰囲気だから、\nシュヴァちも息抜きできるかなって！",
            "choice_data_list": [
                "自分で渡して一緒に行かないのか？",
                "自分で渡して一緒に行かないの？"
            ]
        },
        {
            "name": "ヴィブロス",
            "text": "多分ね、シュヴァち、\n1人で集中したい感じなんだと思うの。"
        },
        {
            "name": "ヴィブロス",
            "text": "がんばってるシュヴァちの、\n邪魔したくないし！"
        },
        {
            "name": "ヴィブロス",
            "text": "あんまり大好きしたら、\nイヤなのかもだから……――"
        },
        {
            "name": "シュヴァルグラン",
            "text": "……。"
        },
        {
            "name": "シュヴァルグラン",
            "text": "……普段、ぐいぐい来るくせに。\n変なところで引くんだ。"
        },
        {
            "name": "シュヴァルグラン",
            "text": "いや……僕のせい、か。"
        },
        {
            "name": "シュヴァルグラン",
            "text": "……でも――"
        },
        {
            "name": "シュヴァルグラン",
            "text": "あ……あのっ。",
            "choice_data_list": [
                "ん？"
            ]
        },
        {
            "name": "シュヴァルグラン",
            "text": "……これ、本当は、\nチャームに添えようと思って……\nでも、やめて。"
        },
        {
            "name": "シュヴァルグラン",
            "text": "でも……。\nこれ……やっぱり、渡しておいてください。"
        },
        {
            "name": "ヴィブロス",
            "text": "――これ、シュヴァちから？",
            "choice_data_list": [
                "ああ",
                "うん"
            ]
        },
        {
            "name": "ヴィブロス",
            "text": "……。"
        },
        {
            "name": "ヴィブロス",
            "text": "ねえ、トレっち！",
            "choice_data_list": [
                "あの子はまだコースにいるぞ",
                "あの子はまだコースにいるよ"
            ]
        },
        {
            "name": "ヴィブロス",
            "text": "！"
        },
        {
            "name": "ヴィブロス",
            "text": "うん、ありがとう～～！"
        },
        {
            "name": "",
            "text": "シュヴァルグランから渡された手紙には、\n『お互い頑張ろう』とたった一言……\nしかし、姉妹を結ぶには十分なようだった。"
        }
    ]
}