{
    "title": "エースVSスピーチ！",
    "no_wrap": false,
    "text_block_list": [
        {
            "name": "",
            "text": "放課後、屋上から威勢のいい声が聞こえ\n様子を見にいくと、カツラギエースがいた――"
        },
        {
            "name": "カツラギエース",
            "text": "――『下を見たって自分の影しかない！\nどんな時でも前を向いて進もう！！』",
            "choice_data_list": [
                "わっ、びっくりした！？"
            ]
        },
        {
            "name": "カツラギエース",
            "text": "あっ、悪い悪い！\n驚かせちまったみたいだな。",
            "choice_data_list": [
                "何をしてたんだ？",
                "何をしてたの？"
            ]
        },
        {
            "name": "カツラギエース",
            "text": "全校集会でやるスピーチの練習だよ。\n秋川理事長から『生徒の士気が上がる話を\nしてほしい』って直々に頼まれたんだ！"
        },
        {
            "name": "カツラギエース",
            "text": "へへっ、あたしのスピーチがみんなを\n変えると思うと、モリモリやる気が\nわいてくるよ……！"
        },
        {
            "name": "カツラギエース",
            "text": "この大一番、絶対モノにしてやるんだ！！",
            "choice_data_list": [
                "かなり気合いが入ってるな……！",
                "かなり気合いが入ってるね……！"
            ]
        },
        {
            "name": "カツラギエース",
            "text": "ああ！　今日は納得いくまで練習するよ！\nよかったら聞いてってくれ！"
        },
        {
            "name": "カツラギエース",
            "text": "『勉強！　レース！　遊びだっていい！\n何か1つのこと、もっと本気出して\nやってみてほしいんだ！！』"
        },
        {
            "name": "カツラギエース",
            "text": "『――つまり気持ちの問題だ！　イヤだって\n思いながらやると、どんどん落ち込む！\n具体的に言うと――』"
        },
        {
            "name": "",
            "text": "カツラギエースのスピーチは、\nその後30分を経過しても\n全く終わる気配がなかった……！"
        },
        {
            "name": "カツラギエース",
            "text": "『――それでも折れそうな時は、\n周りを頼ろう！　だってあたしたちは、\n同じトレセン学園の生徒なんだから！！』",
            "choice_data_list": [
                "一旦、ストップ！……すごい力作だな？",
                "一旦、ストップ！……すごい力作だね？"
            ]
        },
        {
            "name": "カツラギエース",
            "text": "ああ、ここまでで全体の半分ってところだ。"
        },
        {
            "name": "カツラギエース",
            "text": "理事長から期待されてるんだ、\n半端なスピーチはできないだろ？",
            "choice_data_list": [
                "すごいな！手を加えれば更によくなるよ！",
                "すごい！手を加えれば更によくなるね！",
                "（根気強く最後まで聞いてみよう）"
            ]
        },
        {
            "name": "カツラギエース",
            "text": "理事長から期待されてるんだ、\n半端なスピーチはできないだろ？",
            "choice_data_list": [
                "すごいな！手を加えれば更によくなるよ！",
                "すごい！手を加えれば更によくなるね！",
                "（根気強く最後まで聞いてみよう）"
            ]
        },
        {
            "name": "カツラギエース",
            "text": "おっ？　いいアイディアがあるのか？\nぜひ聞かせてくれ！"
        },
        {
            "name": "",
            "text": "冗長なスピーチは聞き流されてしまう。\nビシっと短い言葉でまとめるよう、\nカツラギエースにアドバイスした。"
        },
        {
            "name": "カツラギエース",
            "text": "おお、なるほどな！\n短い方がちゃんと伝わるってことか！"
        },
        {
            "name": "カツラギエース",
            "text": "っしゃーー！！\n最高のスピーチに改良できそうだ！！"
        },
        {
            "name": "",
            "text": "カツラギエースはスピーチに改良を\n重ねていく。だが、再びやる気が暴走して\n長編になりそうで、目が離せないのだった。"
        },
        {
            "name": "カツラギエース",
            "text": "んじゃ、ラストまで突っ走るぜ！"
        },
        {
            "name": "カツラギエース",
            "text": "『――あたしはみんなの力を信じてる！\nやろうぜ、やってやろうぜ、みんな！\nご清聴、ありがとうございました！』",
            "choice_data_list": [
                "（よ、ようやく終わった……！）"
            ]
        },
        {
            "name": "カツラギエース",
            "text": "聞き役がいたから、いい練習になったよ！\nおかげで仕上がりは上々だ。ありがとな！"
        },
        {
            "name": "カツラギエース",
            "text": "よーしっ、みんな待ってろ！\n最高のスピーチをしてやるからなーっ！！"
        },
        {
            "name": "",
            "text": "カツラギエースはヒートアップすると、\n暴走してしまうようだ。本番では、この\n超大作が更に長くならないよう祈るのだった！"
        }
    ]
}