{
    "title": "あたしが渡せるもの",
    "no_wrap": false,
    "text_block_list": [
        {
            "name": "モノローグ",
            "text": "出先から戻る途中。ナイスネイチャたちが\n意外な場所にいたので、話を聞いてみると――"
        },
        {
            "name": "ナイスネイチャ",
            "text": "や、これは研究の一環でして！\n話せば、長くなるんですが……。"
        },
        {
            "name": "ナイスネイチャ",
            "text": "ウチのちっこい弟が、アタシらの絵を\nプレゼントしてくれまして……\nこれがま～、よく描けてるんですよ。"
        },
        {
            "name": "ナイスネイチャ",
            "text": "こりゃお礼したいねって、みんなで話してさ。\nケーキとか？　作ろうってなりまして。"
        },
        {
            "name": "ナイスネイチャ",
            "text": "そのために、映えを勉強してるんです。\n……ほら、あのくらいの子って、派手で\nきらきらーっとしたものが好きだから。"
        },
        {
            "name": "ウインバリアシオン",
            "text": "なるほど……そういうことなら、\n自分もお手伝いするっす！"
        },
        {
            "name": "サウンズオブアース",
            "text": "さあ、コンチェルトを始めようか！\n心のままに！　まずはルバートから！"
        },
        {
            "name": "ナイスネイチャ",
            "text": "ちょ、アース！？　グラニュー糖はさすがに\n量ったほうがいいから！　目分量すぎるって！"
        },
        {
            "name": "ツインターボ",
            "text": "マチタンみてー！　いっぱい\nココアパウダー入れたら真っ黒になった！"
        },
        {
            "name": "マチカネタンホイザ",
            "text": "あわわ……生地がすごいことに……。\nまあでも、濃いめのお味で美味しいかも？"
        },
        {
            "name": "マチカネタンホイザ",
            "text": "これは……なんだ……？\n私たち、ケーキ作ってたはずだよね？"
        },
        {
            "name": "ウインバリアシオン",
            "text": "お、お菓子作りは繊細っすから！\n失敗はあって当然！　次、行くっすよ！"
        },
        {
            "name": "ナイスネイチャ",
            "text": "……うーん。\nケーキの見た目にはなったけど……。"
        },
        {
            "name": "ツインターボ",
            "text": "地味っ！　こんなの、\nふつーのケーキとかわんないぞっ！"
        },
        {
            "name": "ナイスネイチャ",
            "text": "だよねぇ……でも、アタシたちの\n力じゃ、これ以上は……。"
        },
        {
            "name": "ウインバリアシオン",
            "text": "……いや。もうちょっと頑張りましょう。\nネイチャさんたちなら、きっとできるっす。"
        },
        {
            "name": "ウインバリアシオン",
            "text": "ターボさん、イラスト描くの好きっすよね。\n全体のイメージ、決めてもらっていいっすか？\nそれを、みんなで再現すれば――"
        },
        {
            "name": "サウンズオブアース",
            "text": "ドロローソなメロディーア……！\n嗚呼、これではアモローソを伝えられない！"
        },
        {
            "name": "ウインバリアシオン",
            "text": "難易度上がったっすね、デコレーション……\nでも、生地作りとかはもう完璧っすから！"
        },
        {
            "name": "ウインバリアシオン",
            "text": "頑張りましょう！　もう1回！\n次こそ！　上手くいくっす！"
        },
        {
            "name": "ナイスネイチャ",
            "text": "……うん。さっきのより断然いいと思う！\nこれなら……完成としてもいいんじゃない？"
        },
        {
            "name": "ツインターボ",
            "text": "でも見てネイチャ！　ここ！\nターボの絵とちょっと違うっ！"
        },
        {
            "name": "ナイスネイチャ",
            "text": "……それはまあ、あれですよ。\nご愛嬌と言いますか。"
        },
        {
            "name": "ナイスネイチャ",
            "text": "……もしかしたら、もう何回かやれば、\n完璧なのもできるかもだけどさ……\nほら、もう門限も近いし――"
        },
        {
            "name": "ウインバリアシオン",
            "text": "……あたし、知ってるっすよ。\nここで“諦める”ネイチャさんじゃないって。"
        },
        {
            "name": "ナイスネイチャ",
            "text": "シオンさん……。"
        },
        {
            "name": "ウインバリアシオン",
            "text": "最後まで付き合うっす。だから、とことん！\n納得するまでやりましょう！"
        },
        {
            "name": "ウインバリアシオン",
            "text": "――貴方たちなら、やり遂げる。\nあたしはそう信じてるっす！"
        },
        {
            "name": "マチカネタンホイザ",
            "text": "……ど、どうかな？　これはっ……\n私的には、とってもいい気がしてるけど！"
        },
        {
            "name": "サウンズオブアース",
            "text": "ブラヴィーーッッッシモ！！！\nコン・アモーレなメロディーア！！\nこれぞ弟君に送る、最上のムジカだ！"
        },
        {
            "name": "ウインバリアシオン",
            "text": "へへっ……上手くいってよかったっす。",
            "choice_data_list": [
                "君の励ましのおかげだよ",
                "貴方の励ましのおかげだよ"
            ]
        },
        {
            "name": "ウインバリアシオン",
            "text": "…………それも、あるかもっす。\nでもこれ、ただの受け売りで――"
        },
        {
            "name": "ウインバリアシオン",
            "text": "努力しても、届かない時……それでも\n貴方は、その姿勢を褒めてくれました。"
        },
        {
            "name": "ウインバリアシオン",
            "text": "それが、やる気になったから……\n同じようなこと、みんなにしただけっす。",
            "choice_data_list": [
                "そっか。そうだったんだ……"
            ]
        },
        {
            "name": "ウインバリアシオン",
            "text": "……ありがとうございます、トレーナーさん。\n貴方のおかげで、あたし――"
        },
        {
            "name": "ウインバリアシオン",
            "text": "友だちを励ませる、あたしになれたっす。",
            "choice_data_list": [
                "褒められたことを、力にできるのが偉いよ",
                "……顔つき、ちょっとだけ変わったな",
                "……顔つき、ちょっとだけ変わったね",
                "俺の言葉がちゃんと届いて、嬉しい",
                "私の言葉がちゃんと届いて、嬉しい"
            ]
        },
        {
            "name": "ウインバリアシオン",
            "text": "友だちを励ませる、あたしになれたっす。",
            "choice_data_list": [
                "褒められたことを、力にできるのが偉いよ",
                "……顔つき、ちょっとだけ変わったな",
                "……顔つき、ちょっとだけ変わったね",
                "俺の言葉がちゃんと届いて、嬉しい",
                "私の言葉がちゃんと届いて、嬉しい"
            ]
        },
        {
            "name": "ウインバリアシオン",
            "text": "いやいや、自分じゃないっす。偉いのは、\n努力の姿勢を褒められる、貴方の人柄っす。",
            "choice_data_list": [
                "いやいや……その考え方がもう偉い！"
            ]
        },
        {
            "name": "ウインバリアシオン",
            "text": "いやいやいや……トレーナーさんこそ、\nその謙虚な姿勢がもう立派で――",
            "choice_data_list": [
                "いやいやいやシオンのほうが……"
            ]
        },
        {
            "name": "ウインバリアシオン",
            "text": "いやいやいやいやトレーナーさんのほうが……\n……――ぷふっ。"
        },
        {
            "name": "ウインバリアシオン",
            "text": "あははっ！　これ、もうキリないっすね。\nじゃあ、どっちも偉いということで。"
        },
        {
            "name": "ウインバリアシオン",
            "text": "へへっ……そうっすか？\n――そうだと思います、きっと。"
        },
        {
            "name": "ウインバリアシオン",
            "text": "何て言うんすかね……根っこの\n部分は変わってなくても……うん。"
        },
        {
            "name": "ウインバリアシオン",
            "text": "少し、ポジティブになれたかも……なんて。\nちょっとだけ、そう思うんすよ。"
        },
        {
            "name": "ウインバリアシオン",
            "text": "そう思えるように、なったっす。ふふっ。"
        },
        {
            "name": "ウインバリアシオン",
            "text": "へ？　……う、嬉しいっすか？",
            "choice_data_list": [
                "うん。真剣に聞いてくれたってことだから"
            ]
        },
        {
            "name": "ウインバリアシオン",
            "text": "あ……なるほど。そういう……。"
        },
        {
            "name": "ウインバリアシオン",
            "text": "そんなの、当たり前っすよ。\nトレーナーさんの言葉なんすから。"
        },
        {
            "name": "ウインバリアシオン",
            "text": "……救われてるっす。いつも。"
        }
    ]
}