{
    "title": "王道、極めし",
    "no_wrap": false,
    "text_block_list": [
        {
            "name": "モノローグ",
            "text": "――メジロラモーヌに、\n中距離レースを極めてほしい。"
        },
        {
            "name": "モノローグ",
            "text": "その期待は、『オークス』『秋華賞』\n『宝塚記念』『エリザベス女王杯』――"
        },
        {
            "name": "モノローグ",
            "text": "『ジャパンカップ』『大阪杯』\n『天皇賞（秋）』での鮮やかな勝利によって、\n応えてもらえた。",
            "choice_data_list": [
                "（レース史に残る偉大な記録だ！）"
            ]
        },
        {
            "name": "モノローグ",
            "text": "メジロラモーヌにそのことを伝えると――"
        },
        {
            "name": "メジロラモーヌ",
            "text": "そう。",
            "choice_data_list": [
                "（やっぱりどうでもいいか……）"
            ]
        },
        {
            "name": "モノローグ",
            "text": "メジロラモーヌは至高のレースを走り、\nそれに勝利することを至上の愛としている。\n記録そのものに固執しているわけではない。"
        },
        {
            "name": "メジロラモーヌ",
            "text": "……。"
        },
        {
            "name": "メジロラモーヌ",
            "text": "貴方はそれを、\n誇っている。",
            "choice_data_list": [
                "もちろん！"
            ]
        },
        {
            "name": "メジロラモーヌ",
            "text": "とても？",
            "choice_data_list": [
                "とっても！！"
            ]
        },
        {
            "name": "メジロラモーヌ",
            "text": "なら、\nお祝いですわね。",
            "choice_data_list": [
                "……ん？"
            ]
        },
        {
            "name": "メジロラモーヌ",
            "text": "今から言う方々を、\nお呼びしてくださる？"
        },
        {
            "name": "メジロラモーヌ",
            "text": "きっと、\n楽しいパーティーになるわ……。"
        },
        {
            "name": "メジロラモーヌ",
            "text": "――ん。\nいい香り……。"
        },
        {
            "name": "メジロラモーヌ",
            "text": "お2人は、召し上がらなくて？"
        },
        {
            "name": "シンボリルドルフ",
            "text": "ありがとう。茶菓子に羊羹を持ってきたんだ。\n合わせて食べるといい、シリウス。"
        },
        {
            "name": "シンボリルドルフ",
            "text": "羊羹を、よう、噛んで……\n美味しく召し上がれ。"
        },
        {
            "name": "シリウスシンボリ",
            "text": "……。"
        },
        {
            "name": "ルドルフ＆シリウス",
            "text": "……。",
            "choice_data_list": [
                "（き……気まずい！）"
            ]
        },
        {
            "name": "メジロラモーヌ",
            "text": "では……ルドルフとシリウスを、\nお呼びくださる。"
        },
        {
            "name": "モノローグ",
            "text": "2人とも、メジロラモーヌとは縁の深い\nウマ娘だ。確かにパーティーに呼ぶには、\n納得の人選だ。しかし――",
            "choice_data_list": [
                "その2人って、確か……"
            ]
        },
        {
            "name": "モノローグ",
            "text": "あまり仲のよいイメージはない……というか、\n2人が会話しているところを見ると、大体\n剣呑な雰囲気になっている気がするが……。"
        },
        {
            "name": "メジロラモーヌ",
            "text": "よろしくお願いいたしますわね。",
            "choice_data_list": [
                "（と、言われたら頑張るしか……）"
            ]
        },
        {
            "name": "メジロラモーヌ",
            "text": "ふ……。\n2人一緒でなければ、駄目よ。"
        },
        {
            "name": "ルドルフ＆シリウス",
            "text": "もちろん参加するよ。\n断る。"
        },
        {
            "name": "シンボリルドルフ",
            "text": "……シリウス。昔は3人で\n小さなパーティーもしたじゃないか。"
        },
        {
            "name": "シンボリルドルフ",
            "text": "ここ数年、そういう機会もなかったし……\n久しぶりに鼎談するのも悪くないだろう？"
        },
        {
            "name": "シリウスシンボリ",
            "text": "レース以外で、\nお前と語ることなんかねぇ。"
        },
        {
            "name": "モノローグ",
            "text": "このままでは2人一緒には来てもらえない。\nシリウスシンボリは勝気な性格だ、ひたすら\nお願いするより、メジロラモーヌなら多分――",
            "choice_data_list": [
                "……幼馴染と話すのは照れるもんな",
                "……幼馴染と話すのは照れるもんね"
            ]
        },
        {
            "name": "シリウスシンボリ",
            "text": "……。"
        },
        {
            "name": "シリウスシンボリ",
            "text": "……へぇ？　アイツ、\n上手く調教してるらしいな。面白い……。"
        },
        {
            "name": "モノローグ",
            "text": "というわけで、なんとか4人での\n小さなパーティーは始まったものの……。"
        },
        {
            "name": "メジロラモーヌ",
            "text": "ふふ……ああ、\n面白い。"
        },
        {
            "name": "メジロラモーヌ",
            "text": "ねぇ、\nトレーナーさん？",
            "choice_data_list": [
                "俺はすごくドキドキしてるぞ……",
                "私はすごくドキドキしてるよ……"
            ]
        },
        {
            "name": "メジロラモーヌ",
            "text": "どうして。\n子犬のじゃれ合い……可愛いでしょう？"
        },
        {
            "name": "シリウスシンボリ",
            "text": "やっぱりな……。ラモーヌ、\n単なる暇つぶしに巻き込むな。"
        },
        {
            "name": "メジロラモーヌ",
            "text": "わかっていて、いらしたのね。\n甘えん坊さん……仲間外れは、寂しかった？"
        },
        {
            "name": "シリウスシンボリ",
            "text": "ああ、仲間だと思ってたのか？\n愛らしいところもあるじゃねぇか。"
        },
        {
            "name": "シンボリルドルフ",
            "text": "ふふ……懐かしい。知己が揃って、\nなんと心安らぐ時間だろう。",
            "choice_data_list": [
                "（君、ちょっとズレてるぞ）",
                "（貴方、ちょっとズレてるよ）"
            ]
        },
        {
            "name": "シンボリルドルフ",
            "text": "思い出すな。昔もこうして、\n3人集まってピクニックをして……\n私とシリウスが走り出して、君は――"
        },
        {
            "name": "シンボリルドルフ",
            "text": "……いや、覚えていないか。"
        },
        {
            "name": "シリウスシンボリ",
            "text": "オイ、茶番はもうやめろ。\n移動するぞ。"
        },
        {
            "name": "シリウスシンボリ",
            "text": "――走るんだろ。\nアンタが誰かを誘う理由なんざ、1つだ。"
        },
        {
            "name": "メジロラモーヌ",
            "text": "あら、それもご存じ。\nなら……。"
        },
        {
            "name": "メジロラモーヌ",
            "text": "私の“偉大な記録”に、\n花を添えてくださるつもりなのね。"
        },
        {
            "name": "シリウスシンボリ",
            "text": "……余裕だな。\n敗北の味を、祝儀に教えてやるよ。"
        },
        {
            "name": "シンボリルドルフ",
            "text": "花は別途、贈らせてもらおう。\n全力で挑む……それが私からの祝いだ。"
        },
        {
            "name": "メジロラモーヌ",
            "text": "……忘れていない。\n木陰から眺めていた、あの日のこと。"
        },
        {
            "name": "メジロラモーヌ",
            "text": "高らかな笑い声……耳に貼りついている。\nけれど今は……。"
        },
        {
            "name": "メジロラモーヌ",
            "text": "本気のじゃれ合いが、できる。",
            "choice_data_list": [
                "（ラモーヌ……嬉しそう）"
            ]
        },
        {
            "name": "モノローグ",
            "text": "こうして、忙しい中集まった\n旧友3人のじゃれ合いは……\nコースに場所を移して、夕方まで続けられた。"
        }
    ]
}