{
    "title": "ROAD TO THE FUTURE",
    "no_wrap": false,
    "text_block_list": [
        {
            "name": "モノローグ",
            "text": "最初の3年間。ナリタトップロードは\n輝かしい成績を残した。だが――"
        },
        {
            "name": "モノローグ",
            "text": "その3年間、輝いていたのは彼女だけでは\nない。トゥインクル・シリーズにとっては\n一大興盛期だった。"
        },
        {
            "name": "モノローグ",
            "text": "黄金世代とそれを次ぐ者たち。\nまさしく傑物たちが競った華の時代。\nだが――"
        },
        {
            "name": "モノローグ",
            "text": "永遠はありえない。スターウマ娘たちは\n次々にレジェンドとなっていく。"
        },
        {
            "name": "モノローグ",
            "text": "そして――"
        },
        {
            "name": "ジャングルポケット",
            "text": "おっしゃ！　負けねえぞ、カフェ！"
        },
        {
            "name": "マンハッタンカフェ",
            "text": "……よろしくお願いします、ポッケさん。"
        },
        {
            "name": "モノローグ",
            "text": "時代は移り変わる。\n最恐ヤンキー“ジャングルポケット”。\n不思議少女“マンハッタンカフェ”。"
        },
        {
            "name": "モノローグ",
            "text": "新たなウマ娘たちが\nトゥインクル・シリーズの中心に立っていた。"
        },
        {
            "name": "マンハッタンカフェ",
            "text": "時に……ポッケさん。知っていますか？\n伝説の世代のことを。"
        },
        {
            "name": "マンハッタンカフェ",
            "text": "もはや憧れとなってしまった世代。\n黄金世代とそれに続いたウマ娘たちのことを。"
        },
        {
            "name": "ジャングルポケット",
            "text": "ハッ、少しだけな！　だが伝説ってのは\n超えていくためにあるもんだろ？"
        },
        {
            "name": "ジャングルポケット",
            "text": "やるんだよ、カフェ！　俺とお前でな！"
        },
        {
            "name": "ジャングルポケット",
            "text": "伝説なんて、後になればなるほど、\n大げさに語られるもんだ。\nそんなのに屈するかよ。"
        },
        {
            "name": "ジャングルポケット",
            "text": "過去は過去！　今は今！\n俺たちのほうが数段上って見せて……。"
        },
        {
            "name": "？？？",
            "text": "それでは試してみましょう。"
        },
        {
            "name": "ジャングルポケット",
            "text": "ん……？"
        },
        {
            "name": "マンハッタンカフェ",
            "text": "アナタは……。"
        },
        {
            "name": "？？？",
            "text": "伝説の世代は……幻ではありません。\n本当に素晴らしい世代でした。"
        },
        {
            "name": "？？？",
            "text": "そのレベルの高さは今でも通じます。\nでも直接感じてもらえなければ、わからない。"
        },
        {
            "name": "？？？",
            "text": "さらには、いつまでも見たいと願い続ける\nファンも多数います。ですから――"
        },
        {
            "name": "ナリタトップロード",
            "text": "私は今も、ここにいます。\nその力で勝つために。"
        },
        {
            "name": "マンハッタンカフェ",
            "text": "ナリタトップロードさん……。"
        },
        {
            "name": "ジャングルポケット",
            "text": "きやがったな。\n光の化身……生きる伝説……。"
        },
        {
            "name": "ジャングルポケット",
            "text": "ジョートーだ！　俺はこの舞台で、\nあんたとやりたくてウズウズしてたんだ！"
        },
        {
            "name": "ジャングルポケット",
            "text": "教えてくれよ、喧嘩場で！\n絶対に――超えてみせる！"
        },
        {
            "name": "ナリタトップロード",
            "text": "はい。よろしくお願いします。"
        },
        {
            "name": "トプロ＆ポケット",
            "text": "たああああああーーっ！！\nうおらぁあああああーっ！"
        },
        {
            "name": "モノローグ",
            "text": "永遠はありえない。だが刻が過ぎても、\nただ1人……駆け続ける者がいる。"
        },
        {
            "name": "ナリタトップロード",
            "text": "まだまだです！　これが私たちの力！"
        },
        {
            "name": "ジャングルポケット",
            "text": "うおおおおおおっ！？"
        },
        {
            "name": "モノローグ",
            "text": "伝説を受け継ぐ――光となって。"
        },
        {
            "name": "モノローグ",
            "text": "――同日、北海道。"
        },
        {
            "name": "テイエムオペラオー",
            "text": "ふぅ、いいものだね。\nたまにはこんなふうに散策するのも。"
        },
        {
            "name": "テイエムオペラオー",
            "text": "楽しんでいるかい、ドトウ？\n心からリラックスしているかい？"
        },
        {
            "name": "メイショウドトウ",
            "text": "はい～、オペラオーさん。\nなんだか少し慣れませんけど、でも……。"
        },
        {
            "name": "メイショウドトウ",
            "text": "レースから離れてみるのも\n悪くないですね。"
        },
        {
            "name": "テイエムオペラオー",
            "text": "……ああ。\nだが、こうしている今も――"
        },
        {
            "name": "テイエムオペラオー",
            "text": "君は駆けているのだろうね。\nいつかと同じ桜の下を。"
        },
        {
            "name": "テイエムオペラオー",
            "text": "そのひたむきさには頭が下がるよ。\nそして――"
        },
        {
            "name": "テイエムオペラオー",
            "text": "トップロードさん、待っているよ！\n朗報を！"
        },
        {
            "name": "テイエムオペラオー",
            "text": "ボクたちの志の高さを、君の思うまま\n謳い続けてくれたまえ！"
        },
        {
            "name": "ナリタトップロード",
            "text": "トレーナーさん、まだいけます！\n次のレースもまだまだまだ……！"
        },
        {
            "name": "ナリタトップロード",
            "text": "最近、強くなった娘もいますし、\n新しいウマ娘も増えてきました。"
        },
        {
            "name": "ナリタトップロード",
            "text": "ファンのみなさんが応援してくれる限り、\n私、走りたい！　伝えたいです！"
        },
        {
            "name": "ナリタトップロード",
            "text": "レースの熱さ、素晴らしさ、そして――"
        },
        {
            "name": "ナリタトップロード",
            "text": "楽しさを！！",
            "choice_data_list": [
                "ああ、やりきろう！",
                "うん、やりきろう！"
            ]
        },
        {
            "name": "ナリタトップロード",
            "text": "タップちゃん、\n初対戦ありがとうございましたっ。"
        },
        {
            "name": "ナリタトップロード",
            "text": "とてもロマンあふれる走り、\n感動しました！"
        },
        {
            "name": "タップダンスシチー",
            "text": "くっそ、届かない……。強い上に\nこのリーダーシップ……。大物過ぎるだろ。"
        },
        {
            "name": "タップダンスシチー",
            "text": "あー、負けだ負けだ。でも見てろ。\nその器、アタシが絶対に超えてやる！"
        },
        {
            "name": "ナリタトップロード",
            "text": "クリスエスさん、ファインちゃん、\nシャカールちゃん、ミラ子ちゃん、\n今日はよろしくお願いします。"
        },
        {
            "name": "ナリタトップロード",
            "text": "みなさんと一緒に走れて、光栄です。"
        },
        {
            "name": "シンボリクリスエス",
            "text": "ふむ――光栄なのは……me, tooだ。\nThe Legend、ナリタトップロード。"
        },
        {
            "name": "ファインモーション",
            "text": "すごいよねっ。\nずーっと走り続けてるなんて。"
        },
        {
            "name": "エアシャカール",
            "text": "しかも減衰ゼロでな。\nったく、アンタだけは未知数だ。"
        },
        {
            "name": "ヒシミラクル",
            "text": "えへへ、わたしはただ嬉しいってか。\n一緒に走れるようになるなんて、\n夢みたいで。"
        },
        {
            "name": "モノローグ",
            "text": "ナリタトップロードは駆け続ける。\n果てなき道を。"
        },
        {
            "name": "モノローグ",
            "text": "ただひたすら真っ直ぐに、\n多くのウマ娘たちを、\nその輝きで照らしながら。"
        },
        {
            "name": "ナリタトップロード",
            "text": "トレーナーさん、私、あなたと――\nいつまでも進み続けたいです。"
        },
        {
            "name": "ナリタトップロード",
            "text": "道は――頂で終わりじゃない！\n光の道は、頂を超えてどこまでも！"
        },
        {
            "name": "モノローグ",
            "text": "――ナリタトップロード。\nそれは幾多の時代を貫き輝いた、希望の光。"
        },
        {
            "name": "モノローグ",
            "text": "その道は頂に至り、空を超えて、\nそして――今へと続いている。"
        }
    ]
}